ipv8_service.py
ipv8/__init__.py
ipv8/community.py
ipv8/configuration.py
ipv8/database.py
ipv8/lazy_community.py
ipv8/loader.py
ipv8/overlay.py
ipv8/peer.py
ipv8/requestcache.py
ipv8/taskmanager.py
ipv8/util.py
ipv8/REST/__init__.py
ipv8/REST/asyncio_endpoint.py
ipv8/REST/base_endpoint.py
ipv8/REST/dht_endpoint.py
ipv8/REST/identity_endpoint.py
ipv8/REST/isolation_endpoint.py
ipv8/REST/network_endpoint.py
ipv8/REST/noblock_dht_endpoint.py
ipv8/REST/overlays_endpoint.py
ipv8/REST/rest_manager.py
ipv8/REST/root_endpoint.py
ipv8/REST/schema.py
ipv8/REST/tunnel_endpoint.py
ipv8/attestation/__init__.py
ipv8/attestation/communication_manager.py
ipv8/attestation/default_identity_formats.py
ipv8/attestation/identity_formats.py
ipv8/attestation/signed_object.py
ipv8/attestation/identity/__init__.py
ipv8/attestation/identity/attestation.py
ipv8/attestation/identity/community.py
ipv8/attestation/identity/database.py
ipv8/attestation/identity/manager.py
ipv8/attestation/identity/metadata.py
ipv8/attestation/identity/payload.py
ipv8/attestation/schema/__init__.py
ipv8/attestation/schema/manager.py
ipv8/attestation/tokentree/__init__.py
ipv8/attestation/tokentree/token.py
ipv8/attestation/tokentree/tree.py
ipv8/attestation/wallet/__init__.py
ipv8/attestation/wallet/caches.py
ipv8/attestation/wallet/community.py
ipv8/attestation/wallet/database.py
ipv8/attestation/wallet/payload.py
ipv8/attestation/wallet/bonehexact/__init__.py
ipv8/attestation/wallet/bonehexact/algorithm.py
ipv8/attestation/wallet/bonehexact/attestation.py
ipv8/attestation/wallet/bonehexact/structs.py
ipv8/attestation/wallet/pengbaorange/__init__.py
ipv8/attestation/wallet/pengbaorange/algorithm.py
ipv8/attestation/wallet/pengbaorange/attestation.py
ipv8/attestation/wallet/pengbaorange/boudot.py
ipv8/attestation/wallet/pengbaorange/structs.py
ipv8/attestation/wallet/primitives/__init__.py
ipv8/attestation/wallet/primitives/attestation.py
ipv8/attestation/wallet/primitives/boneh.py
pyipv8-3.1.0.dist-info/licenses/LICENSE
pyipv8-3.1.0.dist-info/METADATA
pyipv8-3.1.0.dist-info/WHEEL
pyipv8-3.1.0.dist-info/top_level.txt
pyipv8-3.1.0.dist-info/RECORD
