Metadata-Version: 2.4
Name: pyipv8
Version: 3.1.0
Summary: The Python implementation of the IPV8 library
Home-page: https://github.com/Tribler/py-ipv8
Author: Tribler
Classifier: Development Status :: 5 - Production/Stable
Classifier: Intended Audience :: Developers
Classifier: License :: OSI Approved :: GNU Lesser General Public License v3 (LGPLv3)
Classifier: Natural Language :: English
Classifier: Operating System :: OS Independent
Classifier: Programming Language :: Python :: 3.10
Classifier: Programming Language :: Python :: 3.11
Classifier: Programming Language :: Python :: 3.12
Classifier: Programming Language :: Python :: 3.13
Classifier: Topic :: Scientific/Engineering
Classifier: Topic :: Software Development :: Libraries :: Python Modules
Classifier: Topic :: System :: Distributed Computing
Classifier: Topic :: System :: Networking
License-File: LICENSE
Requires-Dist: cryptography
Requires-Dist: libnacl
Requires-Dist: aiohttp
Requires-Dist: aiohttp_apispec
Requires-Dist: pyOpenSSL
Requires-Dist: pyasn1
Requires-Dist: marshmallow
Requires-Dist: typing-extensions
Requires-Dist: packaging
Provides-Extra: all
Requires-Dist: coverage; extra == "all"
Provides-Extra: tests
Requires-Dist: coverage; extra == "tests"
Dynamic: author
Dynamic: classifier
Dynamic: description
Dynamic: description-content-type
Dynamic: home-page
Dynamic: license-file
Dynamic: provides-extra
Dynamic: requires-dist
Dynamic: summary
